CHANGES.rst
MANIFEST.in
README.rst
setup.cfg
setup.py
version.txt
src/metapensiero/__init__.py
src/metapensiero.asyncio.tasklocal.egg-info/PKG-INFO
src/metapensiero.asyncio.tasklocal.egg-info/SOURCES.txt
src/metapensiero.asyncio.tasklocal.egg-info/dependency_links.txt
src/metapensiero.asyncio.tasklocal.egg-info/namespace_packages.txt
src/metapensiero.asyncio.tasklocal.egg-info/requires.txt
src/metapensiero.asyncio.tasklocal.egg-info/top_level.txt
src/metapensiero/asyncio/__init__.py
src/metapensiero/asyncio/tasklocal/__init__.py