Metadata-Version: 1.1
Name: metapensiero.asyncio.tasklocal
Version: 0.2
Summary: An asyncio's Task-local variable container
Home-page: https://github.com/azazel75/metapensiero.asyncio.tasklocal
Author: Alberto Berti
Author-email: alberto@metapensiero.it
License: GPLv3+
Platform: UNKNOWN
Classifier: Development Status :: 4 - Beta
Classifier: Programming Language :: Python
Classifier: Programming Language :: Python :: 3
Classifier: Programming Language :: Python :: 3.4
Classifier: Programming Language :: Python :: 3.5
